Bottle_ssl_server/__init__.py
Bottle_ssl_server/server.py
bottle_ssl_server-0.1.0.dist-info/licenses/LICENSE.txt
bottle_ssl_server-0.1.0.dist-info/METADATA
bottle_ssl_server-0.1.0.dist-info/WHEEL
bottle_ssl_server-0.1.0.dist-info/entry_points.txt
bottle_ssl_server-0.1.0.dist-info/top_level.txt
bottle_ssl_server-0.1.0.dist-info/RECORD
