Metadata-Version: 2.4
Name: bottle-ssl-server
Version: 0.1.0
Summary: A lightweight SSL-enabled Bottle server with file upload and logging capabilities
Home-page: https://github.com/omegadev21/bottle-ssl-server
Author: Olawale Momurede Abdulsalam
Author-email: muredesalam@example.com
Classifier: Programming Language :: Python :: 3
Classifier: Programming Language :: Python :: 3.6
Classifier: Programming Language :: Python :: 3.7
Classifier: Programming Language :: Python :: 3.8
Classifier: Programming Language :: Python :: 3.9
Classifier: Programming Language :: Python :: 3.10
Classifier: License :: OSI Approved :: MIT License
Classifier: Operating System :: OS Independent
Requires-Python: >=3.6
License-File: LICENSE.txt
Requires-Dist: bottle>=0.12.18
Requires-Dist: cheroot>=8.5.2
Dynamic: author
Dynamic: author-email
Dynamic: classifier
Dynamic: description
Dynamic: description-content-type
Dynamic: home-page
Dynamic: license-file
Dynamic: requires-dist
Dynamic: requires-python
Dynamic: summary
